{"version":3,"kind":"Article","sha256":"961d8d9adb134d030bce9d9a0059277a8896820dabc43ed4a8f9c4ea0429d0d4","slug":"students","location":"/students.md","dependencies":[],"frontmatter":{"title":"Students","subtitle":"Hasan Sarptaş","authors":[{"id":"Hasan Sarptaş","name":"Hasan Sarptaş"}],"keywords":["sarptas","sarptaş","hasan sarptaş","qgis","renewable"],"numbering":{"title":{"offset":1}},"thumbnail":"/olcay_isin-e08924aae0f051564be12eb2debcbb69.jpg","exports":[{"format":"md","filename":"students.md","url":"/students-ce5afe0b7461b205862318617e48898c.md"}]},"mdast":{"type":"root","children":[{"type":"block","children":[{"type":"grid","columns":[12],"children":[{"type":"grid-item","columns":4,"children":[{"type":"image","url":"/olcay_isin-e08924aae0f051564be12eb2debcbb69.jpg","alt":"","width":"200px","align":"left","key":"JU1jAbMQWn","urlSource":"images/students/olcay_isin.jpg"}],"key":"SHck8OUpYE"},{"type":"grid-item","columns":8,"children":[{"type":"paragraph","position":{"start":{"line":19,"column":1},"end":{"line":21,"column":1}},"children":[{"type":"strong","position":{"start":{"line":19,"column":1},"end":{"line":19,"column":1}},"children":[{"type":"text","value":"E. Olcay Işın","position":{"start":{"line":19,"column":1},"end":{"line":19,"column":1}},"key":"MRcbM5aRkS"}],"key":"xB21uDP0O4"},{"type":"text","value":" ","position":{"start":{"line":19,"column":1},"end":{"line":19,"column":1}},"key":"bLe9DDAIxq"},{"type":"break","position":{"start":{"line":19,"column":1},"end":{"line":19,"column":1}},"key":"O6iqNJNvKe"},{"type":"emphasis","position":{"start":{"line":19,"column":1},"end":{"line":19,"column":1}},"children":[{"type":"text","value":"PhD candidate","position":{"start":{"line":19,"column":1},"end":{"line":19,"column":1}},"key":"O6ki36C4DS"}],"key":"p68aD6covb"},{"type":"text","value":", ","position":{"start":{"line":19,"column":1},"end":{"line":19,"column":1}},"key":"JmfR0NdWZy"},{"type":"break","position":{"start":{"line":19,"column":1},"end":{"line":19,"column":1}},"key":"yRpYsA7rRx"},{"type":"text","value":"Research: GIS-based site assessment for district heating systems","position":{"start":{"line":19,"column":1},"end":{"line":19,"column":1}},"key":"vnJYxtGQ0r"}],"key":"EgRcjnZxpR"}],"key":"Mhrb9YQSwf"}],"key":"aAdsaBtks5"},{"type":"grid","columns":[12],"children":[{"type":"grid-item","columns":4,"children":[{"type":"image","url":"/mert_biter-eedb14758fb241837e4b2200d371b7fc.jpg","alt":"","width":"100%","align":"left","key":"j2SLEEtguJ","urlSource":"images/students/mert_biter.jpg"}],"key":"rsaR0EUH3s"},{"type":"grid-item","columns":8,"children":[{"type":"paragraph","position":{"start":{"line":38,"column":1},"end":{"line":40,"column":1}},"children":[{"type":"strong","position":{"start":{"line":38,"column":1},"end":{"line":38,"column":1}},"children":[{"type":"text","value":"Mert Biter","position":{"start":{"line":38,"column":1},"end":{"line":38,"column":1}},"key":"yGImHQ4VI5"}],"key":"fs3wielzlS"},{"type":"text","value":" ","position":{"start":{"line":38,"column":1},"end":{"line":38,"column":1}},"key":"iX0ABBiC0f"},{"type":"break","position":{"start":{"line":38,"column":1},"end":{"line":38,"column":1}},"key":"XBTXpPfrSg"},{"type":"emphasis","position":{"start":{"line":38,"column":1},"end":{"line":38,"column":1}},"children":[{"type":"text","value":"PhD candidate","position":{"start":{"line":38,"column":1},"end":{"line":38,"column":1}},"key":"RAlHoysTJ5"}],"key":"JimhY47i95"},{"type":"text","value":" ","position":{"start":{"line":38,"column":1},"end":{"line":38,"column":1}},"key":"bhfoxMxleW"},{"type":"break","position":{"start":{"line":38,"column":1},"end":{"line":38,"column":1}},"key":"vytjEGqmww"},{"type":"text","value":"Research: Local climate planning, Climate change adaptation","position":{"start":{"line":38,"column":1},"end":{"line":38,"column":1}},"key":"iGXyCOWnKl"}],"key":"Lma0hRY7ZT"}],"key":"zT0Dd19PCb"}],"key":"FYkMDZ0IrP"},{"type":"grid","columns":[12],"children":[{"type":"grid-item","columns":4,"children":[{"type":"image","url":"/benginur_bastabak-44635713f009f932035e079fdd4738e2.jpg","alt":"","width":"200px","align":"left","key":"oLbl0wextw","urlSource":"images/students/benginur_bastabak.jpg"}],"key":"sU6ruiRkr5"},{"type":"grid-item","columns":8,"children":[{"type":"paragraph","position":{"start":{"line":57,"column":1},"end":{"line":59,"column":1}},"children":[{"type":"strong","position":{"start":{"line":57,"column":1},"end":{"line":57,"column":1}},"children":[{"type":"text","value":"Benginur Baştabak","position":{"start":{"line":57,"column":1},"end":{"line":57,"column":1}},"key":"LACKYC3UjD"}],"key":"jrNHDUQsCU"},{"type":"text","value":" ","position":{"start":{"line":57,"column":1},"end":{"line":57,"column":1}},"key":"JH3A75UYin"},{"type":"break","position":{"start":{"line":57,"column":1},"end":{"line":57,"column":1}},"key":"yBxFckVB2q"},{"type":"emphasis","position":{"start":{"line":57,"column":1},"end":{"line":57,"column":1}},"children":[{"type":"text","value":"PhD candidate","position":{"start":{"line":57,"column":1},"end":{"line":57,"column":1}},"key":"rUVH00Y4rm"}],"key":"w8JvOXf8Eg"},{"type":"text","value":", ","position":{"start":{"line":57,"column":1},"end":{"line":57,"column":1}},"key":"RmcZjb94h1"},{"type":"break","position":{"start":{"line":57,"column":1},"end":{"line":57,"column":1}},"key":"Em0de9Vz3y"},{"type":"text","value":"Research: Phytoremediation via energy crops","position":{"start":{"line":57,"column":1},"end":{"line":57,"column":1}},"key":"pVVYIl83Ng"}],"key":"o6zPvhoge0"}],"key":"TTcZW8tl0V"}],"key":"t0P4TWASJg"},{"type":"grid","columns":[12],"children":[{"type":"grid-item","columns":4,"children":[{"type":"image","url":"/gulser_koca-14b65576b318acfe9cf9df6107f57e8b.jpg","alt":"","width":"100%","align":"left","key":"f5YiR53x4G","urlSource":"images/students/gulser_koca.jpg"}],"key":"nklvBK8NrU"},{"type":"grid-item","columns":8,"children":[{"type":"paragraph","position":{"start":{"line":76,"column":1},"end":{"line":78,"column":1}},"children":[{"type":"strong","position":{"start":{"line":76,"column":1},"end":{"line":76,"column":1}},"children":[{"type":"text","value":"Gülser Koca","position":{"start":{"line":76,"column":1},"end":{"line":76,"column":1}},"key":"KEuGJD1Dpr"}],"key":"udPCUAw2PZ"},{"type":"text","value":" ","position":{"start":{"line":76,"column":1},"end":{"line":76,"column":1}},"key":"mDCXKUxvTc"},{"type":"break","position":{"start":{"line":76,"column":1},"end":{"line":76,"column":1}},"key":"n0VZFzyiPg"},{"type":"emphasis","position":{"start":{"line":76,"column":1},"end":{"line":76,"column":1}},"children":[{"type":"text","value":"MSc candidate","position":{"start":{"line":76,"column":1},"end":{"line":76,"column":1}},"key":"eth9PaVrJd"}],"key":"waFIreN55L"},{"type":"text","value":" ","position":{"start":{"line":76,"column":1},"end":{"line":76,"column":1}},"key":"AaVlFihePg"},{"type":"break","position":{"start":{"line":76,"column":1},"end":{"line":76,"column":1}},"key":"aJdpcrckva"},{"type":"text","value":"Research: PV soiling & cleanning methodologies","position":{"start":{"line":76,"column":1},"end":{"line":76,"column":1}},"key":"YRsUtywLmx"}],"key":"winMCSBuqe"}],"key":"fqtecKM3Fa"}],"key":"Q6mPUS3zv0"},{"type":"grid","columns":[12],"children":[{"type":"grid-item","columns":4,"children":[{"type":"image","url":"/mert_yontem-1109ee5e0e80417ffab8d0a4efc7ab78.jpg","alt":"","width":"100%","align":"left","key":"Mbz0MG8nqM","urlSource":"images/students/mert_yontem.jpg"}],"key":"lsYSd7N3m4"},{"type":"grid-item","columns":8,"children":[{"type":"paragraph","position":{"start":{"line":95,"column":1},"end":{"line":97,"column":1}},"children":[{"type":"strong","position":{"start":{"line":95,"column":1},"end":{"line":95,"column":1}},"children":[{"type":"text","value":"Mert Yöntem","position":{"start":{"line":95,"column":1},"end":{"line":95,"column":1}},"key":"NOOKSQwGKZ"}],"key":"SF6FMsvrVS"},{"type":"text","value":" ","position":{"start":{"line":95,"column":1},"end":{"line":95,"column":1}},"key":"ooTbYxmoT9"},{"type":"break","position":{"start":{"line":95,"column":1},"end":{"line":95,"column":1}},"key":"iJ5kfmX0xk"},{"type":"emphasis","position":{"start":{"line":95,"column":1},"end":{"line":95,"column":1}},"children":[{"type":"text","value":"MSc candidate","position":{"start":{"line":95,"column":1},"end":{"line":95,"column":1}},"key":"AL3ABsoPAU"}],"key":"C2tDwSoUER"},{"type":"text","value":" ","position":{"start":{"line":95,"column":1},"end":{"line":95,"column":1}},"key":"RHqSvtRzya"},{"type":"break","position":{"start":{"line":95,"column":1},"end":{"line":95,"column":1}},"key":"GijlcWjlxn"},{"type":"text","value":"Research: -","position":{"start":{"line":95,"column":1},"end":{"line":95,"column":1}},"key":"F4ocO3roRG"}],"key":"R6sRvv0hPQ"}],"key":"Kk64iHfsBH"}],"key":"BQLjmWpM8h"}],"key":"UN0HfRnb1y"}],"key":"xTXeKe5o0g"},"references":{"cite":{"order":[],"data":{}}}}